{"data":{"propertyOrder":{},"properties":{"name":{"name":"name","reference":"scalar","getter":false,"setter":false,"type":"string","array":false},"password":{"name":"password","reference":"scalar","hidden":true,"getter":false,"setter":false,"type":"string","array":false},"isAdmin":{"name":"isAdmin","reference":"scalar","getter":false,"setter":false,"type":"boolean","array":false},"profilePicture":{"name":"profilePicture","reference":"scalar","getter":false,"setter":false,"type":"string","array":false,"optional":true},"productionLogs":{"name":"productionLogs","reference":"1:m","cascade":["persist"],"type":"ProductionLog","array":false}},"props":[{"name":"name","reference":"scalar","getter":false,"setter":false,"type":"string","array":false},{"name":"password","reference":"scalar","hidden":true,"getter":false,"setter":false,"type":"string","array":false},{"name":"isAdmin","reference":"scalar","getter":false,"setter":false,"type":"boolean","array":false},{"name":"profilePicture","reference":"scalar","getter":false,"setter":false,"type":"string","array":false,"optional":true},{"name":"productionLogs","reference":"1:m","cascade":["persist"],"type":"ProductionLog","array":false}],"primaryKeys":[],"filters":{},"hooks":{},"indexes":[{"properties":"name"}],"uniques":[],"checks":[],"concurrencyCheckKeys":{},"className":"User","path":"./src/modules/user/user.entity.ts","name":"User","abstract":false,"constructorParams":[null],"toJsonParams":[],"extends":"CustomBaseEntity","useCache":true,"relations":[{"name":"productionLogs","reference":"1:m","cascade":["persist"],"type":"ProductionLog","array":false}],"collection":"user"},"origin":"./src/modules/user/user.entity.ts","hash":"0a3aab39627c60e153f92afb936767e6","version":"5.7.12"}
